ssltelnet/__init__.py
ssltelnet-0.9.2.dist-info/DESCRIPTION.rst
ssltelnet-0.9.2.dist-info/METADATA
ssltelnet-0.9.2.dist-info/RECORD
ssltelnet-0.9.2.dist-info/WHEEL
ssltelnet-0.9.2.dist-info/metadata.json
ssltelnet-0.9.2.dist-info/top_level.txt
