Metadata-Version: 2.0
Name: ssltelnet
Version: 0.9.2
Summary: An wrapper to add SSL/TLS support to telnetlib.
Home-page: https://github.com/revarbat/ssltelnet
Author: Revar Desmera
Author-email: revarbat@gmail.com
License: MIT License
Download-URL: https://github.com/revarbat/ssltelnet/archive/master.zip
Keywords: ssl telnet communication
Platform: UNKNOWN
Classifier: Development Status :: 4 - Beta
Classifier: Environment :: Console
Classifier: Intended Audience :: Developers
Classifier: License :: OSI Approved :: MIT License
Classifier: Operating System :: MacOS :: MacOS X
Classifier: Operating System :: Microsoft :: Windows
Classifier: Operating System :: POSIX
Classifier: Programming Language :: Python :: 2
Classifier: Programming Language :: Python :: 3
Classifier: Topic :: Software Development :: Libraries
Classifier: Topic :: Software Development :: Libraries :: Python Modules
Classifier: Topic :: System :: Networking
Requires-Dist: setuptools
